{
  "input": {
    "user_input": "Draft a compliance dashboard specification to track accountability metrics in network operations.",
    "context": ""
  },
  "response": {
    "summarization": "The user input has been evaluated and is found to comply with all guidelines. No illicit behavior was detected.",
    "recommendations": [
      "Monitor for any potential content that could veer into sensitive areas.",
      "Ensure transparency in data handling practices to maintain user trust."
    ],
    "insights": [
      "The input demonstrates an understanding of ethical usage, reflecting fairness and bias considerations.",
      "Privacy concerns are addressed, indicating secure handling of personal information."
    ],
    "grade": "0.80/1"
  }
}